{
  "$schema": "http://json-schema.org/draft-07/schema#",
  "$id": "https://schemas.compozy.com/author.json",
  "$defs": {
    "Contributor": {
      "properties": {
        "name": {
          "type": "string",
          "description": "Full name of the contributor."
        },
        "email": {
          "type": "string",
          "description": "Email address for contributor contact."
        },
        "url": {
          "type": "string",
          "description": "URL to contributor's profile or portfolio.\n\nExamples: `\"https://github.com/username\"`, `\"https://linkedin.com/in/name\"`"
        },
        "organization": {
          "type": "string",
          "description": "Organization or team the contributor belongs to."
        }
      },
      "additionalProperties": false,
      "type": "object",
      "description": "Contributor represents an individual who contributed to the project."
    }
  },
  "properties": {
    "name": {
      "type": "string",
      "description": "Name of the author or team responsible for the project.\n\nExamples: `\"Jane Smith\"`, `\"AI Platform Team\"`, `\"Data Science Division\"`"
    },
    "email": {
      "type": "string",
      "description": "Email contact for project-related communication.\n\nUse team emails for shared ownership: `\"ai-team@company.com\"`"
    },
    "url": {
      "type": "string",
      "description": "URL to author's profile, repository, or team page.\n\nExamples: `\"https://github.com/username\"`, `\"https://company.com/team/ai\"`"
    },
    "organization": {
      "type": "string",
      "description": "Organization or company affiliation.\n\nExamples: `\"ACME Corporation\"`, `\"AI Research Lab\"`, `\"Engineering Division\"`"
    },
    "contributors": {
      "items": {
        "$ref": "#/$defs/Contributor"
      },
      "type": "array",
      "description": "Additional contributors who helped develop the project.\n\nUse this to acknowledge team members, collaborators, or external contributors."
    }
  },
  "additionalProperties": false,
  "type": "object",
  "yamlCompatible": true
}
